nonebot_plugin_waiter-0.7.1.dist-info/METADATA
nonebot_plugin_waiter-0.7.1.dist-info/WHEEL
nonebot_plugin_waiter/__init__.py
nonebot_plugin_waiter/config.py
nonebot_plugin_waiter-0.7.1.dist-info/RECORD
