Metadata-Version: 2.1
Name: nonebot-plugin-waiter
Version: 0.7.1
Summary: An alternative for got-and-reject in Nonebot
Author-Email: RF-Tar-Railt <3165388245@qq.com>
License: MIT
Requires-Python: >=3.9
Requires-Dist: nonebot2>=2.3.0
